essay_eval/__init__.py
essay_eval/functions.py
essay_eval/lookup.py
essay_eval/data/mrc_psycholing.pkl
essay_eval-0.0.1.dist-info/LICENSE
essay_eval-0.0.1.dist-info/METADATA
essay_eval-0.0.1.dist-info/WHEEL
essay_eval-0.0.1.dist-info/top_level.txt
essay_eval-0.0.1.dist-info/RECORD
